binance_history/__init__.py
binance_history/api.py
binance_history/cli.py
binance_history/config.py
binance_history/constants.py
binance_history/exceptions.py
binance_history/utils.py
binance_history-0.1.7.dist-info/LICENSE
binance_history-0.1.7.dist-info/METADATA
binance_history-0.1.7.dist-info/WHEEL
binance_history-0.1.7.dist-info/entry_points.txt
binance_history-0.1.7.dist-info/RECORD
