Metadata-Version: 2.1
Name: binance-history
Version: 0.1.7
Summary: Fetch binance historical klines or trades easily.
Home-page: https://github.com/xzmeng/binance-history
License: MIT
Keywords: crypto,cryptocurrency,backtest,backtesting,BTC,binance
Author: Meng Xiangzhuo
Author-email: aumo@foxmail.com
Requires-Python: >=3.8,<4.0
Classifier: License :: OSI Approved :: MIT License
Classifier: Programming Language :: Python :: 3
Classifier: Programming Language :: Python :: 3.8
Classifier: Programming Language :: Python :: 3.9
Classifier: Programming Language :: Python :: 3.10
Classifier: Programming Language :: Python :: 3.11
Requires-Dist: httpx (>=0.23.1,<0.24.0)
Requires-Dist: loguru (>=0.6.0,<0.7.0)
Requires-Dist: pandas (>=1.5.2,<2.0.0)
Requires-Dist: pendulum (>=2.1.2,<3.0.0)
Project-URL: Documentation, https://binance-history.readthedocs.io/
Project-URL: Repository, https://github.com/xzmeng/binance-history
